pytexttyper/__init__.py
pytexttyper/main.py
PyTextTyper-1.0.1.dist-info/LICENSE
PyTextTyper-1.0.1.dist-info/METADATA
PyTextTyper-1.0.1.dist-info/WHEEL
PyTextTyper-1.0.1.dist-info/top_level.txt
PyTextTyper-1.0.1.dist-info/RECORD
