Metadata-Version: 2.1
Name: PyTextTyper
Version: 1.0.1
Summary: PyTextTyper is a text engine written in python which prints text to the console, fully complete with animations, colors, and ASCII art!
Home-page: https://github.com/Ollielab/PyTextTyper
Author: Ollielab
Author-email: mail@ollielab.xyz
License: MIT
Classifier: Programming Language :: Python :: 3
Classifier: License :: OSI Approved :: MIT License
Classifier: Operating System :: OS Independent
Requires-Python: >=3.6
License-File: LICENSE
Requires-Dist: art (==5.8)
